expviz/__init__.py
expviz/expviz.py
expviz/version.py
chatgpt_score-0.0.2.dist-info/METADATA
chatgpt_score-0.0.2.dist-info/WHEEL
chatgpt_score-0.0.2.dist-info/top_level.txt
chatgpt_score-0.0.2.dist-info/RECORD
