Metadata-Version: 2.1
Name: chatgpt-score
Version: 0.0.2
Home-page: https://github.com/fuzihaofzh/chatgpt_score
Author: 
Author-email: 
Keywords: Shell env
Classifier: Programming Language :: Python :: 3.8
Requires-Dist: openai
